hassediagram/__init__.py
hassediagram/cycles.py
hassediagram/hasse_diagram.py
hasse_diagram-1.2.dist-info/METADATA
hasse_diagram-1.2.dist-info/WHEEL
hasse_diagram-1.2.dist-info/top_level.txt
hasse_diagram-1.2.dist-info/RECORD
