Metadata-Version: 2.4
Name: hasse-diagram
Version: 1.2
Summary: Plot Hasse Diagram in Python
Home-page: https://github.com/anras5/hasse-diagram
Author: Filip Marciniak
Author-email: filip.marciniak15@gmail.com
Project-URL: Bug Tracker, https://github.com/anras5/hasse-diagram/issues
Classifier: Programming Language :: Python :: 3
Classifier: License :: OSI Approved :: MIT License
Classifier: Operating System :: OS Independent
Requires-Python: >=3.10
Requires-Dist: numpy>=2.0.0
Requires-Dist: matplotlib>=3.9.0
Requires-Dist: networkx>=3.3
Requires-Dist: graphviz>=0.20.3
